a_pandas_ex_fastloc/LICENSE
a_pandas_ex_fastloc/README.MD
a_pandas_ex_fastloc/__init__.py
a_pandas_ex_fastloc/requirements.txt
a_pandas_ex_fastloc/thirdparty.json
a_pandas_ex_fastloc-0.11.dist-info/LICENSE.rst
a_pandas_ex_fastloc-0.11.dist-info/METADATA
a_pandas_ex_fastloc-0.11.dist-info/WHEEL
a_pandas_ex_fastloc-0.11.dist-info/top_level.txt
a_pandas_ex_fastloc-0.11.dist-info/RECORD
