Metadata-Version: 2.1
Name: a-pandas-ex-fastloc
Version: 0.11
Summary: Up to 25 times faster than df.loc by combining np.select and numexpr.evaluate (works with utf-8)
Home-page: https://github.com/hansalemaos/a_pandas_ex_fastloc
Author: Johannes Fischer
Author-email: <aulasparticularesdealemaosp@gmail.com>
License: MIT
Keywords: numexpr,numpy,loc,iloc,pandas,series
Classifier: Development Status :: 4 - Beta
Classifier: Programming Language :: Python :: 3 :: Only
Classifier: Programming Language :: Python :: 3.9
Classifier: Topic :: Scientific/Engineering :: Visualization
Classifier: Topic :: Software Development :: Libraries :: Python Modules
Classifier: Topic :: Text Editors :: Text Processing
Classifier: Topic :: Text Processing :: General
Classifier: Topic :: Text Processing :: Indexing
Classifier: Topic :: Text Processing :: Filters
Classifier: Topic :: Utilities
License-File: LICENSE.rst
Requires-Dist: numexpr
Requires-Dist: numpy
Requires-Dist: pandas
Requires-Dist: regex
Requires-Dist: ujson
